README.rst
setup.py
VoiceCom.egg-info/PKG-INFO
VoiceCom.egg-info/SOURCES.txt
VoiceCom.egg-info/dependency_links.txt
VoiceCom.egg-info/entry_points.txt
VoiceCom.egg-info/top_level.txt
voicecom/__init__.py
voicecom/paths.py