Metadata-Version: 1.1
Name: VoiceCom
Version: 0.0.2rc2
Summary: An open source Voice-User-Interface (VUI)
Home-page: https://github.com/koehlja/VoiceCom
Author: https://github.com/koehlja
Author-email: UNKNOWN
License: MIT License
Keywords: voice,speech,recognition,computer
Platform: UNKNOWN
Classifier: Development Status :: 1 - Planning
Classifier: Intended Audience :: Developers
Classifier: Intended Audience :: End Users/Desktop
Classifier: License :: OSI Approved :: MIT License
Classifier: Programming Language :: Python
Classifier: Programming Language :: Python :: 2
Classifier: Programming Language :: Python :: 2.3
Classifier: Programming Language :: Python :: 2.4
Classifier: Programming Language :: Python :: 2.5
Classifier: Programming Language :: Python :: 2.6
Classifier: Programming Language :: Python :: 2.7
Classifier: Programming Language :: Python :: 2 :: Only
Classifier: Topic :: Utilities
Classifier: Topic :: Home Automation
Classifier: Topic :: Multimedia :: Sound/Audio :: Speech
Classifier: Topic :: Scientific/Engineering :: Human Machine Interfaces
